Heron/__init__.py
Heron/constants.py
Heron/decorators.py
Heron/general_utils.py
Heron/settings_default.json
Heron/Operations/Sinks/Hardware/Arduino_Serial_Out/arduino_serial_out_com.py
Heron/Operations/Sinks/Hardware/Arduino_Serial_Out/arduino_serial_out_worker.py
Heron/Operations/Sinks/Hardware/__top__/ignore.gitignore
Heron/Operations/Sinks/Saving/Save_Array_to_Binary/save_numpy_array_to_binary_com.py
Heron/Operations/Sinks/Saving/Save_Array_to_Binary/save_numpy_array_to_binary_worker.py
Heron/Operations/Sinks/Saving/Save_Pandas_DF/save_pandas_df_com.py
Heron/Operations/Sinks/Saving/Save_Pandas_DF/save_pandas_df_worker.py
Heron/Operations/Sinks/Saving/__top__/ignore.gitignore
Heron/Operations/Sources/Input/Key_Press/key_press_com.py
Heron/Operations/Sources/Input/Key_Press/key_press_worker.py
Heron/Operations/Sources/Input/User_Input/user_input_com.py
Heron/Operations/Sources/Input/User_Input/user_input_worker.py
Heron/Operations/Sources/Input/__top__/ignore.gitignore
Heron/Operations/Sources/Signal/Timer/timer_com.py
Heron/Operations/Sources/Signal/Timer/timer_worker.py
Heron/Operations/Sources/Signal/__top__/ignore.gitignore
Heron/Operations/Transforms/General/User Defined Function 1I1O/user_defined_function_1i1o_com.py
Heron/Operations/Transforms/General/User Defined Function 1I1O/user_defined_function_1i1o_worker.py
Heron/Operations/Transforms/General/Visualiser/visualiser_com.py
Heron/Operations/Transforms/General/Visualiser/visualiser_worker.py
Heron/Operations/Transforms/General/__top__/ignore.gitignore
Heron/communication/forwarders.py
Heron/communication/sink_com.py
Heron/communication/sink_worker.py
Heron/communication/socket_for_serialization.py
Heron/communication/source_com.py
Heron/communication/source_worker.py
Heron/communication/ssh_com.py
Heron/communication/transform_com.py
Heron/communication/transform_worker.py
Heron/docs/.buildinfo
Heron/docs/Makefile
Heron/docs/conf.py
Heron/docs/index.rst
Heron/docs/make.bat
Heron/docs/source/conf.py
Heron_42ad-0.8.4.dist-info/LICENSE
Heron_42ad-0.8.4.dist-info/METADATA
Heron_42ad-0.8.4.dist-info/WHEEL
Heron_42ad-0.8.4.dist-info/entry_points.txt
Heron_42ad-0.8.4.dist-info/top_level.txt
Heron_42ad-0.8.4.dist-info/RECORD
