Metadata-Version: 2.1
Name: Heron-42ad
Version: 0.8.4
Summary: Heron Node baed experiment designer
Home-page: https://github.com/Heron-Repositories/Heron
Author: George Dimitriadis
Author-email: George Dimitriadis <gdimitri@hotmail.com>
License: MIT License
Project-URL: Homepage, https://github.com/Heron-Repositories/Heron/tree/main
Project-URL: Documentation, https://heron-42ad.readthedocs.io/en/latest/index.html
Project-URL: Issues, https://github.com/Heron-Repositories/Heron/issues
Keywords: Node-based,experiment
Classifier: Development Status :: 3 - Alpha
Classifier: Intended Audience :: Science/Research
Classifier: License :: OSI Approved :: MIT License
Classifier: Operating System :: POSIX :: Linux
Classifier: Operating System :: Microsoft :: Windows
Classifier: Programming Language :: Python :: 3.11
Requires-Python: >=3.11
License-File: LICENSE
Requires-Dist: pyzmq>=20.0
Requires-Dist: numpy
Requires-Dist: dearpygui>=1.2
Requires-Dist: paramiko
Requires-Dist: opencv-python>=4.5
Requires-Dist: pandas
Requires-Dist: h5py
Requires-Dist: tornado
Requires-Dist: pynput
Requires-Dist: pyserial
Requires-Dist: psutil
